LICENSE
MANIFEST.in
README.md
setup.cfg
setup.py
django_pythonic_menu/__init__.py
django_pythonic_menu/apps.py
django_pythonic_menu/menu.py
django_pythonic_menu/models.py
django_pythonic_menu/tests.py
django_pythonic_menu.egg-info/PKG-INFO
django_pythonic_menu.egg-info/SOURCES.txt
django_pythonic_menu.egg-info/dependency_links.txt
django_pythonic_menu.egg-info/requires.txt
django_pythonic_menu.egg-info/top_level.txt
django_pythonic_menu/templatetags/__init__.py
django_pythonic_menu/templatetags/pythonic_menu.py