Metadata-Version: 1.1
Name: django-pythonic-menu
Version: 0.0.6
Summary: Python based menu for django
Home-page: https://github.com/YuriMalinov/django-pythonic-menu/
Author: Yuri Malinov
Author-email: yurik.m@gmail.com
License: MIT
Keywords: django menu python
Platform: UNKNOWN
Classifier: Development Status :: 4 - Beta
Classifier: Intended Audience :: Developers
Classifier: Topic :: Software Development :: Libraries :: Python Modules
Classifier: License :: OSI Approved :: MIT License
Classifier: Programming Language :: Python :: 2
Classifier: Programming Language :: Python :: 2.7
Classifier: Programming Language :: Python :: 3
Classifier: Programming Language :: Python :: 3.3
Classifier: Programming Language :: Python :: 3.4
Classifier: Programming Language :: Python :: 3.5
